il4pred2/Feature/.DS_Store
il4pred2/Feature/human_alt2.csv
il4pred2/Feature/human_main.csv
il4pred2/Feature/mouse_alt1.csv
il4pred2/Feature/mouse_main.csv
il4pred2/Python_scripts/__init__.py
il4pred2/Python_scripts/il4pred2.py
il4pred2/model/.DS_Store
il4pred2/model/human_et_alternate1_dpc.pkl
il4pred2/model/human_et_alternate_2.pkl
il4pred2/model/human_mlp_main.pkl
il4pred2/model/mouse_lr_alternate_1.pkl
il4pred2/model/mouse_mlp_main.pkl
il4pred2/model/mouse_rf_alternate_2.pkl
il4pred2/pfeature_standalone/.DS_Store
il4pred2/pfeature_standalone/LICENSE
il4pred2/pfeature_standalone/Pfeature_Descriptors.pdf
il4pred2/pfeature_standalone/README.md
il4pred2/pfeature_standalone/README.txt
il4pred2/pfeature_standalone/Requirement.txt
il4pred2/pfeature_standalone/Screenshot.png
il4pred2/pfeature_standalone/envfile
il4pred2/pfeature_standalone/pfeature_bin.py
il4pred2/pfeature_standalone/pfeature_comp.py
il4pred2/pfeature_standalone/pfeature_pssm.py
il4pred2/pfeature_standalone/protein.fa
il4pred2/pfeature_standalone/protein.seq
il4pred2/pfeature_standalone/Data/AAIndexNames.csv
il4pred2/pfeature_standalone/Data/Grantham.csv
il4pred2/pfeature_standalone/Data/PhysicoChemical.csv
il4pred2/pfeature_standalone/Data/README.md
il4pred2/pfeature_standalone/Data/Schneider-Wrede.csv
il4pred2/pfeature_standalone/Data/aa_attr_group.csv
il4pred2/pfeature_standalone/Data/aaind.txt
il4pred2/pfeature_standalone/Data/aaindex.csv
il4pred2/pfeature_standalone/Data/aaindices.csv
il4pred2/pfeature_standalone/Data/atom.csv
il4pred2/pfeature_standalone/Data/bin_di.csv
il4pred2/pfeature_standalone/Data/bonds.csv
il4pred2/pfeature_standalone/Data/can_pat.csv
il4pred2/pfeature_standalone/Data/data
il4pred2/pfeature_standalone/Data/z_aaindex.csv
il4pred2-1.0.dist-info/METADATA
il4pred2-1.0.dist-info/WHEEL
il4pred2-1.0.dist-info/entry_points.txt
il4pred2-1.0.dist-info/top_level.txt
il4pred2-1.0.dist-info/RECORD
