Metadata-Version: 2.4
Name: il4pred2
Version: 1.0
Summary: A tool to predict il4-inducing peptides
Home-page: https://github.com/raghavagps/il4pred2
Requires-Python: >=3.6
Requires-Dist: pandas
Requires-Dist: numpy
Requires-Dist: scikit-learn==1.2.1
Dynamic: description
Dynamic: description-content-type
Dynamic: home-page
Dynamic: requires-dist
Dynamic: requires-python
Dynamic: summary
